README
setup.py
pixplz/__init__.py
pixplz/fetch.py
pixplz/fetch_audio.py
pixplz.egg-info/PKG-INFO
pixplz.egg-info/SOURCES.txt
pixplz.egg-info/dependency_links.txt
pixplz.egg-info/entry_points.txt
pixplz.egg-info/requires.txt
pixplz.egg-info/top_level.txt