Metadata-Version: 1.0
Name: pixplz
Version: 0.0.6
Summary: Fetch some images to use as casual training data
Home-page: https://github.com/paulfitz/pixplz
Author: Paul Fitzpatrick
Author-email: paulfitz@alum.mit.edu
License: UNKNOWN
Platform: UNKNOWN
